functions_wrapper/__init__.py
functions_wrapper-1.0.2.dist-info/LICENSE
functions_wrapper-1.0.2.dist-info/METADATA
functions_wrapper-1.0.2.dist-info/WHEEL
functions_wrapper-1.0.2.dist-info/top_level.txt
functions_wrapper-1.0.2.dist-info/RECORD
