Metadata-Version: 2.1
Name: functions_wrapper
Version: 1.0.2
Summary: Run multiple endpoints on Google Cloud Functions and Amazon Lambda
Home-page: https://github.com/av1m/functions-multiple-endpoints
Author: av1m
Author-email: a@avim.eu
Project-URL: Source, https://github.com/av1m/functions-multiple-endpoints
Project-URL: Bug Tracker, https://github.com/av1m/functions-multiple-endpoints/issues
Classifier: Intended Audience :: Developers
Classifier: Programming Language :: Python :: 3
Classifier: License :: OSI Approved :: MIT License
Classifier: Operating System :: OS Independent
Requires-Python: >=3.6
License-File: LICENSE
